enums.py
languages.py
trending.py
utils.py
git_trend-0.5.5.dist-info/LICENSE
git_trend-0.5.5.dist-info/METADATA
git_trend-0.5.5.dist-info/WHEEL
git_trend-0.5.5.dist-info/entry_points.txt
git_trend-0.5.5.dist-info/top_level.txt
git_trend-0.5.5.dist-info/RECORD
