Metadata-Version: 2.1
Name: git-trend
Version: 0.5.5
Summary: A Python CLI tool for fetching trending github repositories and developers
Home-page: https://github.com/manojkarthick/git-trend
Author: Manoj Karthick
Author-email: manojkarthick@ymail.com
License: MIT License
Keywords: github,trending,repositories,developers,languages
Platform: UNKNOWN
Classifier: Development Status :: 4 - Beta
Classifier: Intended Audience :: Developers
Classifier: License :: OSI Approved :: MIT License
Classifier: Operating System :: OS Independent
Requires-Python: >=3.6
Requires-Dist: termcolor
Requires-Dist: beautifulsoup4
Requires-Dist: requests
Requires-Dist: prettytable
